wurfl/__init__.py
wurfl/user.py
wurfl_paypal-1.0.0.dist-info/LICENSE
wurfl_paypal-1.0.0.dist-info/METADATA
wurfl_paypal-1.0.0.dist-info/WHEEL
wurfl_paypal-1.0.0.dist-info/entry_points.txt
wurfl_paypal-1.0.0.dist-info/top_level.txt
wurfl_paypal-1.0.0.dist-info/RECORD
